arduino_hid_emulator/__init__.py
arduino_hid_emulator/arduino.py
arduino_hid_emulator/constants.py
arduino_hid_emulator/keyboard.py
arduino_hid_emulator/mouse.py
examples/__init__.py
examples/complex_demo.py
examples/simple_keyboard.py
examples/simple_mouse.py
examples/simple_mouse_calibration.py
tests/__init__.py
tests/test_arduino.py
tests/test_keyboard.py
tests/test_mouse.py
arduino_hid_emulator-0.4.1.dist-info/LICENSE
arduino_hid_emulator-0.4.1.dist-info/METADATA
arduino_hid_emulator-0.4.1.dist-info/WHEEL
arduino_hid_emulator-0.4.1.dist-info/top_level.txt
arduino_hid_emulator-0.4.1.dist-info/RECORD
