Metadata-Version: 2.1
Name: arduino-hid-emulator
Version: 0.4.1
Summary: A Python library for controlling Arduino HID devices
Home-page: https://github.com/mvandrew/arduino-hid-emulator
Author: Andrey Mishchenko
Author-email: msav@msav.ru
Classifier: Programming Language :: Python :: 3
Classifier: License :: OSI Approved :: GNU General Public License v3 (GPLv3)
Classifier: Operating System :: OS Independent
Requires-Python: >=3.6
License-File: LICENSE
Requires-Dist: pyserial
Requires-Dist: pyautogui
